latex_generator_fotonchicc/__init__.py
latex_generator_fotonchicc/latex_generator.py
latex_generator_fotonchicc-0.0.1.dist-info/METADATA
latex_generator_fotonchicc-0.0.1.dist-info/WHEEL
latex_generator_fotonchicc-0.0.1.dist-info/licenses/LICENSE
latex_generator_fotonchicc-0.0.1.dist-info/RECORD
