Metadata-Version: 2.4
Name: latex_generator_fotonchicc
Version: 0.0.1
Summary: A library to generate LaTeX code for tables and images.
Author-email: fotonchicc <sv.markelova11@gmail.com>
License-Expression: MIT
License-File: LICENSE
Classifier: License :: OSI Approved :: MIT License
Classifier: Operating System :: OS Independent
Classifier: Programming Language :: Python :: 3
Requires-Python: >=3.9
